captain_pycard-0.9.11.dist-info/DESCRIPTION.rst
captain_pycard-0.9.11.dist-info/METADATA
captain_pycard-0.9.11.dist-info/RECORD
captain_pycard-0.9.11.dist-info/WHEEL
captain_pycard-0.9.11.dist-info/metadata.json
captain_pycard-0.9.11.dist-info/top_level.txt
pycard/__init__.py
pycard/card.py
pycard/holder.py
