Metadata-Version: 2.0
Name: captain-pycard
Version: 0.9.11
Summary: A simple library for payment card validation
Home-page: https://github.com/orokusaki/pycard/
Author: Michael Angeletti
Author-email: michael@angelettigroup.com
License: UNKNOWN
Platform: UNKNOWN
Classifier: Environment :: Web Environment
Classifier: Intended Audience :: Developers
Classifier: License :: OSI Approved :: GNU General Public License v3 (GPLv3)
Classifier: Operating System :: OS Independent
Classifier: Programming Language :: Python
Classifier: Development Status :: 4 - Beta
Classifier: Topic :: Utilities
